[
  {
    "id": "1",
    "name": "Yahoo主要",
    "src": "https://news.yahoo.co.jp/rss/topics/top-picks.xml",
    "url": "https://news.yahoo.co.jp/",
    "category": ["Yahoo","Yahoo1","Yahoo2","Yahoo3","Yahoo4"]
  },
  {
    "id": "2",
    "name": "エンタメ",
    "src": "https://news.yahoo.co.jp/rss/topics/entertainment.xml",
    "url": "https://news.yahoo.co.jp/",
    "category": ["Web"]
  },
  {
    "id": "3",
    "name": "天気",
    "src": "https://rss-weather.yahoo.co.jp/rss/days/4410.xml",
    "url": "https://news.yahoo.co.jp/",
    "category": ["Yahoo", "Web"]
  },
  {
    "id": "4",
    "name": "Yahoo主要A",
    "src": "https://news.yahoo.co.jp/rss/topics/top-picks.xml",
    "url": "https://news.yahoo.co.jp/",
    "category": ["Yahoo"]
  },
  {
    "id": "5",
    "name": "エンタメB",
    "src": "https://news.yahoo.co.jp/rss/topics/entertainment.xml",
    "url": "https://news.yahoo.co.jp/",
    "category": ["Web"]
  },
  {
    "id": "6",
    "name": "天気B",
    "src": "https://rss-weather.yahoo.co.jp/rss/days/4410.xml",
    "url": "https://news.yahoo.co.jp/",
    "category": ["Yahoo", "Web"]
  }
]
